odoo10_addon_stock_change_price_at_date-10.0.1.0.0.99.dev3-py3.8-nspkg.pth
odoo/addons/stock_change_price_at_date/README.rst
odoo/addons/stock_change_price_at_date/__init__.py
odoo/addons/stock_change_price_at_date/__manifest__.py
odoo/addons/stock_change_price_at_date/i18n/stock_change_price_at_date.pot
odoo/addons/stock_change_price_at_date/models/__init__.py
odoo/addons/stock_change_price_at_date/models/account_move.py
odoo/addons/stock_change_price_at_date/models/product_product.py
odoo/addons/stock_change_price_at_date/readme/CONTRIBUTORS.rst
odoo/addons/stock_change_price_at_date/readme/DESCRIPTION.rst
odoo/addons/stock_change_price_at_date/readme/USAGE.rst
odoo/addons/stock_change_price_at_date/static/description/icon.png
odoo/addons/stock_change_price_at_date/static/description/index.html
odoo/addons/stock_change_price_at_date/tests/__init__.py
odoo/addons/stock_change_price_at_date/tests/test_change_price_at_date.py
odoo/addons/stock_change_price_at_date/wizards/__init__.py
odoo/addons/stock_change_price_at_date/wizards/stock_change_standard_price.py
odoo/addons/stock_change_price_at_date/wizards/stock_change_standard_price.xml
odoo10_addon_stock_change_price_at_date-10.0.1.0.0.99.dev3.dist-info/METADATA
odoo10_addon_stock_change_price_at_date-10.0.1.0.0.99.dev3.dist-info/WHEEL
odoo10_addon_stock_change_price_at_date-10.0.1.0.0.99.dev3.dist-info/namespace_packages.txt
odoo10_addon_stock_change_price_at_date-10.0.1.0.0.99.dev3.dist-info/top_level.txt
odoo10_addon_stock_change_price_at_date-10.0.1.0.0.99.dev3.dist-info/RECORD
