Metadata-Version: 2.1
Name: odoo10-addon-stock-change-price-at-date
Version: 10.0.1.0.0.99.dev3
Summary: This module allows to fill in a date in the standard wizard that changes product price. That helps accountant to add some product past values
Home-page: https://acsone.eu
Author: ACSONE SA/NV,Odoo Community Association (OCA)
Author-email: support@odoo-community.org
License: AGPL-3
Platform: UNKNOWN
Classifier: Programming Language :: Python
Classifier: Framework :: Odoo
Classifier: Framework :: Odoo :: 10.0
Classifier: License :: OSI Approved :: GNU Affero General Public License v3
Requires-Python: ~=2.7
Requires-Dist: odoo <10.1dev,>=10.0
